setup.py
blockscore/__init__.py
blockscore/client.py
blockscore/error.py
blockscore.egg-info/PKG-INFO
blockscore.egg-info/SOURCES.txt
blockscore.egg-info/dependency_links.txt
blockscore.egg-info/requires.txt
blockscore.egg-info/top_level.txt
blockscore/api/__init__.py
blockscore/api/__init__.pyc
blockscore/api/companies.py
blockscore/api/companies.pyc
blockscore/api/people.py
blockscore/api/people.pyc
blockscore/api/question_set.pyc
blockscore/api/question_sets.py
blockscore/api/question_sets.pyc
blockscore/api/verification.pyc
blockscore/api/watchlist.pyc
blockscore/api/watchlists.py
blockscore/api/watchlists.pyc
blockscore/http_client/__init__.py
blockscore/http_client/__init__.pyc
blockscore/http_client/auth_handler.py
blockscore/http_client/auth_handler.pyc
blockscore/http_client/error_handler.py
blockscore/http_client/error_handler.pyc
blockscore/http_client/request_handler.py
blockscore/http_client/request_handler.pyc
blockscore/http_client/response.py
blockscore/http_client/response.pyc
blockscore/http_client/response_handler.py
blockscore/http_client/response_handler.pyc